Metadata-Version: 2.1
Name: lasertools-spectrumprocess
Version: 0.0.1.1
Summary: A module to process spectra
Home-page: https://github.com/lasertools/lasertools_spectrumprocess
Author-email: 68578865+brittonm@users.noreply.github.com
License: GPLv3
Download-URL: https://github.com/lasertools/lasertools_spectrumprocess/archive/refs/tags/v_0_0_1_1.tar.gz
Platform: UNKNOWN
Classifier: Programming Language :: Python :: 3.9
License-File: LICENSE
